learn_to_pick/__init__.py
learn_to_pick/base.py
learn_to_pick/metrics.py
learn_to_pick/model_repository.py
learn_to_pick/pick_best.py
learn_to_pick/vw_logger.py
learn_to_pick-0.0.3.dist-info/LICENSE
learn_to_pick-0.0.3.dist-info/METADATA
learn_to_pick-0.0.3.dist-info/WHEEL
learn_to_pick-0.0.3.dist-info/top_level.txt
learn_to_pick-0.0.3.dist-info/RECORD
