Metadata-Version: 2.1
Name: learn-to-pick
Version: 0.0.3
Summary: a python library for online learning RL loops, specialized for Contextual Bandit scenarios.
Home-page: https://github.com/VowpalWabbit/learn_to_pick
Author: VowpalWabbit
License: UNKNOWN
Platform: UNKNOWN
Requires-Python: >=3.8
License-File: LICENSE
Requires-Dist: numpy (>=1.24.4)
Requires-Dist: pandas (>=2.0.3)
Requires-Dist: parameterfree
Requires-Dist: pyskiplist
Requires-Dist: sentence-transformers (>=2.2.2)
Requires-Dist: torch
Requires-Dist: vowpal-wabbit-next (==0.7.0)
Provides-Extra: dev
Requires-Dist: black (==23.10.0) ; extra == 'dev'
Requires-Dist: pytest ; extra == 'dev'
